{
  "086520.KQ": {
    "timestamp": "2026-02-09T19:40:41.567086",
    "raw_data": {
      "ticker": "086520.KQ",
      "name": "에코프로",
      "technical": {
        "price": 52700,
        "weekly_return": -2.77,
        "macd": "Bearish",
        "vol_spike": 0.57,
        "is_bullish": false
      },
      "fundamental": {
        "per": 0.0,
        "pbr": 13.36,
        "roe": 0.0,
        "target_price": "N/A"
      },
      "dart": {
        "quarterly_trend": [],
        "debt_ratio": "N/A"
      },
      "investor": {
        "foreign_net": 0,
        "institution_net": 0
      },
      "news": [
        "[\"AI 거품 아냐\" 돌아온 외국인…반도체株 급등 코스피 5290선 마감 [시...] 지난주 시장을 흔들었던 인공지능(AI) 과잉 투자 논란이 다소 완화되면서 코스피·코스닥이 모두 4% 이상 급등했다. AI 인프라 투자는 적정 수준이라는 젠슨 황 엔비디아 최고경영자(CEO)의 버블 우려 불식 발언 또한 시장 심리에... ",
        "['V자 급등락' 국내 증시 대응 어떻게?…\"이 주식들 사모아라\"] 국내증시에서 급락과 급등을 반복하는 롤러코스터장세가 이어지고 있다. 증권가에서는 주도주 비중을 확대하는 전략이 유효하다고 본다. 9일 거래소에서 코스피는 전 거래일 대비 208.90포인트(4.10%) 오른 5298.04에 거래를 마쳤다. 기관투자자와... ",
        "[코스피 떠난 외국인 돌아왔다…외인·기관 쌍끌이에 ‘5300’ 턱밑 마...] 지난주 11조원 매도 외국인 매수세 전환 코스닥 4% 상승한 1127.55 거래 마감 코스피가 4% 넘게 올라 5300선 목전에서 장을 마친 9일 서울 중구 하나은행 본점에서 직원들이 증시와 환율을 모니터하고 있다. [연합] [헤럴드경제=김지윤 기자]... ",
        "[[오늘증시] 코스피 5300 코앞서 마감… 코스닥도 4% 넘게 올라] [오늘증시]는 오늘 국내 증권 시장의 현황을 점검합니다. 9일 코스피가 지난주의 낙폭을 회복하며 5300 코앞에서 장을 마쳤다. 코스닥도 힘을 받으며 4%대의 상승률을 보였다. 이날 한국거래소에 따르면 코스피는 전 거래일 대비 208.... ",
        "[[김지영의 생존투자] 운용사가 상장사 ‘픽’했다? ETF 규모 급증에 혼...] 국내 상장지수펀드(ETF) 시장으로 자금이 급속히 유입되면서 자산운용사들의 상장사 지분 공시가 잇따르고 있다. ETF 설정액 증가에 따라 편입 종목의 보유 지분이 기계적으로 확대되며 대량보유 공시가 늘어난 것으로, 개별 기업에 대한 운용사의... "
      ]
    }
  },
  "196170.KQ": {
    "timestamp": "2026-02-09T19:40:41.655791",
    "raw_data": {
      "ticker": "196170.KQ",
      "name": "알테오젠",
      "technical": {
        "price": 52700,
        "weekly_return": -2.77,
        "macd": "Bearish",
        "vol_spike": 0.57,
        "is_bullish": false
      },
      "fundamental": {
        "per": 164.4,
        "pbr": 55.69,
        "roe": 0.0,
        "target_price": "N/A"
      },
      "dart": {
        "quarterly_trend": [],
        "debt_ratio": "N/A"
      },
      "investor": {
        "foreign_net": 0,
        "institution_net": 0
      },
      "news": [
        "[\"AI 거품 아냐\" 돌아온 외국인…반도체株 급등 코스피 5290선 마감 [시...] 지난주 시장을 흔들었던 인공지능(AI) 과잉 투자 논란이 다소 완화되면서 코스피·코스닥이 모두 4% 이상 급등했다. AI 인프라 투자는 적정 수준이라는 젠슨 황 엔비디아 최고경영자(CEO)의 버블 우려 불식 발언 또한 시장 심리에... ",
        "['V자 급등락' 국내 증시 대응 어떻게?…\"이 주식들 사모아라\"] 국내증시에서 급락과 급등을 반복하는 롤러코스터장세가 이어지고 있다. 증권가에서는 주도주 비중을 확대하는 전략이 유효하다고 본다. 9일 거래소에서 코스피는 전 거래일 대비 208.90포인트(4.10%) 오른 5298.04에 거래를 마쳤다. 기관투자자와... ",
        "[코스피 떠난 외국인 돌아왔다…외인·기관 쌍끌이에 ‘5300’ 턱밑 마...] 지난주 11조원 매도 외국인 매수세 전환 코스닥 4% 상승한 1127.55 거래 마감 코스피가 4% 넘게 올라 5300선 목전에서 장을 마친 9일 서울 중구 하나은행 본점에서 직원들이 증시와 환율을 모니터하고 있다. [연합] [헤럴드경제=김지윤 기자]... ",
        "[[오늘증시] 코스피 5300 코앞서 마감… 코스닥도 4% 넘게 올라] [오늘증시]는 오늘 국내 증권 시장의 현황을 점검합니다. 9일 코스피가 지난주의 낙폭을 회복하며 5300 코앞에서 장을 마쳤다. 코스닥도 힘을 받으며 4%대의 상승률을 보였다. 이날 한국거래소에 따르면 코스피는 전 거래일 대비 208.... ",
        "[코스피, 미국발 훈풍에 4% 급등 5,300선 목전 마감…코스닥 상승(종합...] 외국인·기관 '사자'…개인은 역대 최대 순매도 삼성전자·하이닉스 급등…금융주는 하락 코스피가 9일 미국발 훈풍에 4% 넘게 급등해 5,300선 목전에서 장을 마쳤다. 이날 코스피는 전장보다 208.90포인트(4.10%) 오른 5,298.04에 장을 마치며... "
      ]
    }
  },
  "277810.KQ": {
    "timestamp": "2026-02-09T19:40:41.672240",
    "raw_data": {
      "ticker": "277810.KQ",
      "name": "레인보우로보틱스",
      "technical": {
        "price": 52700,
        "weekly_return": -2.77,
        "macd": "Bearish",
        "vol_spike": 0.57,
        "is_bullish": false
      },
      "fundamental": {
        "per": 6870.0,
        "pbr": 101.45,
        "roe": 0.0,
        "target_price": "N/A"
      },
      "dart": {
        "quarterly_trend": [],
        "debt_ratio": "N/A"
      },
      "investor": {
        "foreign_net": 0,
        "institution_net": 0
      },
      "news": [
        "[\"AI 거품 아냐\" 돌아온 외국인…반도체株 급등 코스피 5290선 마감 [시...] 지난주 시장을 흔들었던 인공지능(AI) 과잉 투자 논란이 다소 완화되면서 코스피·코스닥이 모두 4% 이상 급등했다. AI 인프라 투자는 적정 수준이라는 젠슨 황 엔비디아 최고경영자(CEO)의 버블 우려 불식 발언 또한 시장 심리에... ",
        "['V자 급등락' 국내 증시 대응 어떻게?…\"이 주식들 사모아라\"] 국내증시에서 급락과 급등을 반복하는 롤러코스터장세가 이어지고 있다. 증권가에서는 주도주 비중을 확대하는 전략이 유효하다고 본다. 9일 거래소에서 코스피는 전 거래일 대비 208.90포인트(4.10%) 오른 5298.04에 거래를 마쳤다. 기관투자자와... ",
        "[[오늘증시] 코스피 5300 코앞서 마감… 코스닥도 4% 넘게 올라] [오늘증시]는 오늘 국내 증권 시장의 현황을 점검합니다. 9일 코스피가 지난주의 낙폭을 회복하며 5300 코앞에서 장을 마쳤다. 코스닥도 힘을 받으며 4%대의 상승률을 보였다. 이날 한국거래소에 따르면 코스피는 전 거래일 대비 208.... ",
        "[코스피, 미국발 훈풍에 4% 급등 5,300선 목전 마감…코스닥 상승(종합...] 외국인·기관 '사자'…개인은 역대 최대 순매도 삼성전자·하이닉스 급등…금융주는 하락 코스피가 9일 미국발 훈풍에 4% 넘게 급등해 5,300선 목전에서 장을 마쳤다. 이날 코스피는 전장보다 208.90포인트(4.10%) 오른 5,298.04에 장을 마치며... ",
        "[\"사흘 만에 5300선 재돌파\"…코스피·코스닥, AI 훈풍에 동반 급등 [마...] 코스피가 사흘 만에 다시 5300선을 장중 돌파하며 상승 마감했다. 간밤 뉴욕증시에서 반도체주가 강세를 보인 가운데 인공지능(AI) 투자 심리 회복과 기관 매수세가 지수 상승을 이끌었다. 한국거래소에 따르면 9일 코스피는 전... "
      ]
    }
  },
  "141080.KQ": {
    "timestamp": "2026-02-09T19:40:41.683071",
    "raw_data": {
      "ticker": "141080.KQ",
      "name": "리가켐바이오",
      "technical": {
        "price": 52700,
        "weekly_return": -2.77,
        "macd": "Bearish",
        "vol_spike": 0.57,
        "is_bullish": false
      },
      "fundamental": {
        "per": 0.0,
        "pbr": 11.71,
        "roe": 0.0,
        "target_price": "N/A"
      },
      "dart": {
        "quarterly_trend": [],
        "debt_ratio": "N/A"
      },
      "investor": {
        "foreign_net": 0,
        "institution_net": 0
      },
      "news": [
        "[리가켐바이오, 소티오로부터 ADC 기술이전 마일스톤 수령 예정] 리가켐바이오(141080)가 글로벌 파트너사인 소티오 바이오텍(SOTIO Biotech)으로부터 항체약물접합체(ADC) 플랫폼 기술이전 계약에 따른 마일스톤(단계별 기술료)을 받을 예정이라고 9일 밝혔다. 암세포를 잡는 ‘유도미사일’로 불리는 ADC는... ",
        "[\"AI 거품 아냐\" 돌아온 외국인…반도체株 급등 코스피 5290선 마감 [시...] 지난주 시장을 흔들었던 인공지능(AI) 과잉 투자 논란이 다소 완화되면서 코스피·코스닥이 모두 4% 이상 급등했다. AI 인프라 투자는 적정 수준이라는 젠슨 황 엔비디아 최고경영자(CEO)의 버블 우려 불식 발언 또한 시장 심리에... ",
        "['V자 급등락' 국내 증시 대응 어떻게?…\"이 주식들 사모아라\"] 국내증시에서 급락과 급등을 반복하는 롤러코스터장세가 이어지고 있다. 증권가에서는 주도주 비중을 확대하는 전략이 유효하다고 본다. 9일 거래소에서 코스피는 전 거래일 대비 208.90포인트(4.10%) 오른 5298.04에 거래를 마쳤다. 기관투자자와... ",
        "[코스피 떠난 외국인 돌아왔다…외인·기관 쌍끌이에 ‘5300’ 턱밑 마...] 지난주 11조원 매도 외국인 매수세 전환 코스닥 4% 상승한 1127.55 거래 마감 코스피가 4% 넘게 올라 5300선 목전에서 장을 마친 9일 서울 중구 하나은행 본점에서 직원들이 증시와 환율을 모니터하고 있다. [연합] [헤럴드경제=김지윤 기자]... ",
        "[[오늘증시] 코스피 5300 코앞서 마감… 코스닥도 4% 넘게 올라] [오늘증시]는 오늘 국내 증권 시장의 현황을 점검합니다. 9일 코스피가 지난주의 낙폭을 회복하며 5300 코앞에서 장을 마쳤다. 코스닥도 힘을 받으며 4%대의 상승률을 보였다. 이날 한국거래소에 따르면 코스피는 전 거래일 대비 208.... "
      ]
    }
  },
  "028300.KQ": {
    "timestamp": "2026-02-09T19:40:41.696966",
    "raw_data": {
      "ticker": "028300.KQ",
      "name": "HLB",
      "technical": {
        "price": 52700,
        "weekly_return": -2.77,
        "macd": "Bearish",
        "vol_spike": 0.57,
        "is_bullish": false
      },
      "fundamental": {
        "per": 0.0,
        "pbr": 18.32,
        "roe": 0.0,
        "target_price": "N/A"
      },
      "dart": {
        "quarterly_trend": [],
        "debt_ratio": "N/A"
      },
      "investor": {
        "foreign_net": 0,
        "institution_net": 0
      },
      "news": [
        "[\"AI 거품 아냐\" 돌아온 외국인…반도체株 급등 코스피 5290선 마감 [시...] 지난주 시장을 흔들었던 인공지능(AI) 과잉 투자 논란이 다소 완화되면서 코스피·코스닥이 모두 4% 이상 급등했다. AI 인프라 투자는 적정 수준이라는 젠슨 황 엔비디아 최고경영자(CEO)의 버블 우려 불식 발언 또한 시장 심리에... ",
        "[코스피, 반도체 투톱 반등에 3.8% 상승한 5280선 [장중시황]] 인공지능(AI) 관련 우려가 일부 완화되고, 비트코인이 반등하는 등 위험자산 선호심리 회복에 국내 증시도 강세다. 외국인과 기관의 동반 매수세에 코스피·코스닥이 모두 상승했다. 9일 오후 1시 38분 기준 코스피는 전일... ",
        "[[서울데이터랩]케어젠 -5.12% 하락으로 코스닥 시총 상위 주목] 코스닥 시가총액 상위 종목들이 전반적으로 상승세를 보이고 있다. 9일 한국거래소에 따르면, 시가총액 1위 에코프로(086520)는 현재가 156,600원으로 전 거래일 대비 0.51% 상승하고 있다. 시가총액은 21조 2625억원이며... ",
        "[코스피, 3거래일 만에 5300선 탈환…코스닥 2.84%↑[개장시황]] 코스피지수가 장 초반 4% 넘게 급등하며 3거래일 만에 5300선을 탈환했다. 간밤 뉴욕증시에서 반도체주가 강세를 보이는 등 인공지능(AI) 투자 심리가 살아난 영향이다. 9시 오전 9시 15분 코스피는 전일 대비 197.92p(3.89%) 상승한... ",
        "[ABL바이오, 사노피 변수에 20만원선 붕괴…HLB·루닛도 악재 부각[바이...] 이 기사는 2026년02월02일 08시10분에 팜이데일리 프리미엄 콘텐츠로 선공개 되었습니다. 지난달 30일 국내 바이오 섹터에서는 에이비엘바이오(298380)가 사노피에 기술이전한 'ABL301'의 개발 우선순위가 조정되자 장 중 한 때 20%대까지... "
      ]
    }
  },
  "058470.KQ": {
    "timestamp": "2026-02-09T19:40:41.759250",
    "raw_data": {
      "ticker": "058470.KQ",
      "name": "리노공업",
      "technical": {
        "price": 52700,
        "weekly_return": -2.77,
        "macd": "Bearish",
        "vol_spike": 0.57,
        "is_bullish": false
      },
      "fundamental": {
        "per": 50.08,
        "pbr": 10.9,
        "roe": 0.0,
        "target_price": "N/A"
      },
      "dart": {
        "quarterly_trend": [],
        "debt_ratio": "N/A"
      },
      "investor": {
        "foreign_net": 0,
        "institution_net": 0
      },
      "news": [
        "[\"AI 거품 아냐\" 돌아온 외국인…반도체株 급등 코스피 5290선 마감 [시...] 지난주 시장을 흔들었던 인공지능(AI) 과잉 투자 논란이 다소 완화되면서 코스피·코스닥이 모두 4% 이상 급등했다. AI 인프라 투자는 적정 수준이라는 젠슨 황 엔비디아 최고경영자(CEO)의 버블 우려 불식 발언 또한 시장 심리에... ",
        "['V자 급등락' 국내 증시 대응 어떻게?…\"이 주식들 사모아라\"] 국내증시에서 급락과 급등을 반복하는 롤러코스터장세가 이어지고 있다. 증권가에서는 주도주 비중을 확대하는 전략이 유효하다고 본다. 9일 거래소에서 코스피는 전 거래일 대비 208.90포인트(4.10%) 오른 5298.04에 거래를 마쳤다. 기관투자자와... ",
        "[[오늘증시] 코스피 5300 코앞서 마감… 코스닥도 4% 넘게 올라] [오늘증시]는 오늘 국내 증권 시장의 현황을 점검합니다. 9일 코스피가 지난주의 낙폭을 회복하며 5300 코앞에서 장을 마쳤다. 코스닥도 힘을 받으며 4%대의 상승률을 보였다. 이날 한국거래소에 따르면 코스피는 전 거래일 대비 208.... ",
        "[코스피, 'V자 반등' 성공…외인·기관 '쌍끌이' 5300선 등락] 삼성전자 4.92%·SK하이닉스 5.72%↑ 코스닥도 4%대 강세 환율 9.2원 하락 [더팩트ㅣ이한림 기자] 전 거래일 장중 5000선을 내준 코스피가 외인과 기관의 쌍끌이 매수세로 5300선을 오가는 'V자 반등'에 성공했다. 9일 한국거래소에 따르면 이날... ",
        "[기관·외인 쌍끌이 매수에…4% 상승 코스피, 5300 턱밑 마감 [시황]] 코스피가 9일 기관 및 외국인 투자자 매수세에 힘입어 상승 마감했다. 한국거래소에 따르면, 이날 코스피 지수는 전 거래일 대비 208.90포인트(4.10%) 오른 5298.04에 거래를 마쳤다. 지수는 전장보다 209.96포인트(4.13%) 오른 5299.10로... "
      ]
    }
  },
  "000250.KQ": {
    "timestamp": "2026-02-09T19:40:41.802871",
    "raw_data": {
      "ticker": "000250.KQ",
      "name": "삼천당제약",
      "technical": {
        "price": 52700,
        "weekly_return": -2.77,
        "macd": "Bearish",
        "vol_spike": 0.57,
        "is_bullish": false
      },
      "fundamental": {
        "per": 0.0,
        "pbr": 46.94,
        "roe": 0.0,
        "target_price": "N/A"
      },
      "dart": {
        "quarterly_trend": [],
        "debt_ratio": "N/A"
      },
      "investor": {
        "foreign_net": 0,
        "institution_net": 0
      },
      "news": [
        "[\"AI 거품 아냐\" 돌아온 외국인…반도체株 급등 코스피 5290선 마감 [시...] 지난주 시장을 흔들었던 인공지능(AI) 과잉 투자 논란이 다소 완화되면서 코스피·코스닥이 모두 4% 이상 급등했다. AI 인프라 투자는 적정 수준이라는 젠슨 황 엔비디아 최고경영자(CEO)의 버블 우려 불식 발언 또한 시장 심리에... ",
        "['V자 급등락' 국내 증시 대응 어떻게?…\"이 주식들 사모아라\"] 국내증시에서 급락과 급등을 반복하는 롤러코스터장세가 이어지고 있다. 증권가에서는 주도주 비중을 확대하는 전략이 유효하다고 본다. 9일 거래소에서 코스피는 전 거래일 대비 208.90포인트(4.10%) 오른 5298.04에 거래를 마쳤다. 기관투자자와... ",
        "[코스피 떠난 외국인 돌아왔다…외인·기관 쌍끌이에 ‘5300’ 턱밑 마...] 지난주 11조원 매도 외국인 매수세 전환 코스닥 4% 상승한 1127.55 거래 마감 코스피가 4% 넘게 올라 5300선 목전에서 장을 마친 9일 서울 중구 하나은행 본점에서 직원들이 증시와 환율을 모니터하고 있다. [연합] [헤럴드경제=김지윤 기자]... ",
        "[[오늘증시] 코스피 5300 코앞서 마감… 코스닥도 4% 넘게 올라] [오늘증시]는 오늘 국내 증권 시장의 현황을 점검합니다. 9일 코스피가 지난주의 낙폭을 회복하며 5300 코앞에서 장을 마쳤다. 코스닥도 힘을 받으며 4%대의 상승률을 보였다. 이날 한국거래소에 따르면 코스피는 전 거래일 대비 208.... ",
        "[코스피, 미국발 훈풍에 4% 급등 5,300선 목전 마감…코스닥 상승(종합...] 외국인·기관 '사자'…개인은 역대 최대 순매도 삼성전자·하이닉스 급등…금융주는 하락 코스피가 9일 미국발 훈풍에 4% 넘게 급등해 5,300선 목전에서 장을 마쳤다. 이날 코스피는 전장보다 208.90포인트(4.10%) 오른 5,298.04에 장을 마치며... "
      ]
    }
  },
  "950160.KQ": {
    "timestamp": "2026-02-09T19:40:41.818513",
    "raw_data": {
      "ticker": "950160.KQ",
      "name": "코오롱티슈진",
      "technical": {
        "price": 52700,
        "weekly_return": -2.77,
        "macd": "Bearish",
        "vol_spike": 0.57,
        "is_bullish": false
      },
      "fundamental": {
        "per": 0.0,
        "pbr": 44.08,
        "roe": 0.0,
        "target_price": "N/A"
      },
      "dart": {
        "quarterly_trend": [],
        "debt_ratio": "N/A"
      },
      "investor": {
        "foreign_net": 0,
        "institution_net": 0
      },
      "news": [
        "[\"AI 거품 아냐\" 돌아온 외국인…반도체株 급등 코스피 5290선 마감 [시...] 지난주 시장을 흔들었던 인공지능(AI) 과잉 투자 논란이 다소 완화되면서 코스피·코스닥이 모두 4% 이상 급등했다. AI 인프라 투자는 적정 수준이라는 젠슨 황 엔비디아 최고경영자(CEO)의 버블 우려 불식 발언 또한 시장 심리에... ",
        "['V자 급등락' 국내 증시 대응 어떻게?…\"이 주식들 사모아라\"] 국내증시에서 급락과 급등을 반복하는 롤러코스터장세가 이어지고 있다. 증권가에서는 주도주 비중을 확대하는 전략이 유효하다고 본다. 9일 거래소에서 코스피는 전 거래일 대비 208.90포인트(4.10%) 오른 5298.04에 거래를 마쳤다. 기관투자자와... ",
        "[[오늘증시] 코스피 5300 코앞서 마감… 코스닥도 4% 넘게 올라] [오늘증시]는 오늘 국내 증권 시장의 현황을 점검합니다. 9일 코스피가 지난주의 낙폭을 회복하며 5300 코앞에서 장을 마쳤다. 코스닥도 힘을 받으며 4%대의 상승률을 보였다. 이날 한국거래소에 따르면 코스피는 전 거래일 대비 208.... ",
        "[코스피, 'V자 반등' 성공…외인·기관 '쌍끌이' 5300선 등락] 삼성전자 4.92%·SK하이닉스 5.72%↑ 코스닥도 4%대 강세 환율 9.2원 하락 [더팩트ㅣ이한림 기자] 전 거래일 장중 5000선을 내준 코스피가 외인과 기관의 쌍끌이 매수세로 5300선을 오가는 'V자 반등'에 성공했다. 9일 한국거래소에 따르면 이날... ",
        "[\"사흘 만에 5300선 재돌파\"…코스피·코스닥, AI 훈풍에 동반 급등 [마...] 코스피가 사흘 만에 다시 5300선을 장중 돌파하며 상승 마감했다. 간밤 뉴욕증시에서 반도체주가 강세를 보인 가운데 인공지능(AI) 투자 심리 회복과 기관 매수세가 지수 상승을 이끌었다. 한국거래소에 따르면 9일 코스피는 전... "
      ]
    }
  },
  "140410.KQ": {
    "timestamp": "2026-02-09T19:40:42.842381",
    "raw_data": {
      "ticker": "140410.KQ",
      "name": "메지온",
      "technical": {
        "price": 147400,
        "weekly_return": -6.65,
        "macd": "Bearish",
        "vol_spike": 0.45,
        "is_bullish": true
      },
      "fundamental": {
        "per": 0.0,
        "pbr": 119.26,
        "roe": 0.0,
        "target_price": "N/A"
      },
      "dart": {
        "quarterly_trend": [],
        "debt_ratio": "N/A"
      },
      "investor": {
        "foreign_net": 0,
        "institution_net": 0
      },
      "news": [
        "[[서울데이터랩]케어젠 -5.12% 하락으로 코스닥 시총 상위 주목] 코스닥 시가총액 상위 종목들이 전반적으로 상승세를 보이고 있다. 9일 한국거래소에 따르면, 시가총액 1위 에코프로(086520)는 현재가 156,600원으로 전 거래일 대비 0.51% 상승하고 있다. 시가총액은 21조 2625억원이며... ",
        "['미공개 정보 이용' LG家 구연경 이번주 선고…징역 1년 구형] 미공개 정보를 이용해 주식을 취득했다는 의혹으로 재판에 넘겨진 고(故) 구본무 LG그룹 선대 회장의 장녀인 구연경 LG복지재단 대표와 남편 윤관 블루런벤처스(BRV) 대표에 대한 1심 판단이 이번 주 나온다. 8일 법조계에 따르면 서울남부지법... ",
        "[외국인 3조 ‘던지기’…코스피, 5089선 마감, 변동성 장세 지속] 거시경제 둔화 우려와 인공지능(AI) 수익성 불확실성이 겹치며 한국 증시가 이틀 연속 하락 마감했다. 글로벌 위험자산 선호도가 위축된 가운데, 반도체 투자 심리를 되살릴 재료가 부족했다는 평가가 나온다. 6일 코스피지수는 전... ",
        "[[서울데이터랩]레인보우로보틱스 -7.45% 하락 코스닥 하락세 주도] 코스닥 시가총액 상위 종목들이 대체로 하락세를 보이고 있다. 6일 한국거래소에 따르면, 시가총액 1위인 에코프로(086520)는 현재가 157,700원으로 전 거래일 대비 5.85% 하락하고 있다. 시가총액은 21조 4,119억원이며... ",
        "[코스피, 외인·기관 매도에 4900선 거래…코스닥도 약세] 외국인과 기관의 동반 매도세에 6일 코스피가 장 초반 급락세다. 코스닥도 4%대 약세 흐름이다. 간밤 뉴욕 증시가 인공지능(AI) 투자 과열 우려로 대형 기술주 중심의 하락세를 보이는 등 글로벌 위험 선호 심리가 급격하게 위축되며... "
      ]
    }
  },
  "214150.KQ": {
    "timestamp": "2026-02-09T19:40:42.872332",
    "raw_data": {
      "ticker": "214150.KQ",
      "name": "클래시스",
      "technical": {
        "price": 147400,
        "weekly_return": -6.65,
        "macd": "Bearish",
        "vol_spike": 0.45,
        "is_bullish": true
      },
      "fundamental": {
        "per": 37.62,
        "pbr": 8.52,
        "roe": 0.0,
        "target_price": "N/A"
      },
      "dart": {
        "quarterly_trend": [],
        "debt_ratio": "N/A"
      },
      "investor": {
        "foreign_net": 0,
        "institution_net": 0
      },
      "news": [
        "[코스피 반등하자 개미 2.8조 ‘팔자’…5270선으로 후퇴] 코스피 지수가 5300선에서 등락을 반복하고 있다. 뉴욕증시 훈풍에 힘입어 장 초반 급등세를 보였으나 차익실현 매물이 출회하며 상승 폭을 제한하는 것으로 해석된다. 9일 엠피닥터에 따르면 이날 오후 1시 36분 기준 코스피는... ",
        "[[서울데이터랩]케어젠 -5.12% 하락으로 코스닥 시총 상위 주목] 코스닥 시가총액 상위 종목들이 전반적으로 상승세를 보이고 있다. 9일 한국거래소에 따르면, 시가총액 1위 에코프로(086520)는 현재가 156,600원으로 전 거래일 대비 0.51% 상승하고 있다. 시가총액은 21조 2625억원이며... ",
        "[[서울데이터랩]레인보우로보틱스 -7.45% 하락 코스닥 하락세 주도] 코스닥 시가총액 상위 종목들이 대체로 하락세를 보이고 있다. 6일 한국거래소에 따르면, 시가총액 1위인 에코프로(086520)는 현재가 157,700원으로 전 거래일 대비 5.85% 하락하고 있다. 시가총액은 21조 4,119억원이며... ",
        "[컨센서스 밑돌자 주가 급락... 파마리서치, 빛바랜 ‘역대급 실적’] 파마리서치가 지난해 역대 최고 실적을 써냈지만 주가는 급락했다. 실적이 시장 예상치(컨센서스)를 밑돌면서 실망감을 안겨줬기 때문으로 분석된다. 이 회사의 시가총액(시총)은 지난해 상반기 5조원을 돌파하며 미용 의료기기 업계 1위에... ",
        "[미 테크주 쇼크에 코스피 약세 출발…삼전 3%·SK하닉 4% 약세] 간밤 뉴욕 증시에서 기술주가 급락하면서 코스피도 약세 출발했다. 특히 AMD나 마이크론 등 반도체 기업에서 데이터센터 매출이 시장 기대치에 미치지 못하면서 삼성전자와 SK하이닉스도 하락 중이다. 5일 오전 9시11분 기준 코스피는 전 거래일... "
      ]
    }
  }
}